ohmysportsfeedspy/MySportsFeeds_API.py
ohmysportsfeedspy/__init__.py
ohmysportsfeedspy/v1_0.py
ohmysportsfeedspy/v1_1.py
ohmysportsfeedspy/v1_2.py
ohmysportsfeedspy/v2_0.py
ohmysportsfeedspy/v2_1.py
ohmysportsfeedspy-2.1.1.dist-info/METADATA
ohmysportsfeedspy-2.1.1.dist-info/WHEEL
ohmysportsfeedspy-2.1.1.dist-info/top_level.txt
ohmysportsfeedspy-2.1.1.dist-info/RECORD
